{
  "events": [
    {
      "matchup": "Qingdao Hainiu vs Dalian Yingbo",
      "league": "CHINA - CHINESE SUPER LEAGUE",
      "bet": "ML - Dalian Yingbo",
      "betbck_odds": "-128",
      "pinnacle_nvp": "-146",
      "ev": "5.59%",
      "ev_val": 0.0559,
      "start_time": "08/03 07:00",
      "event_id": 1612115025
    },
    {
      "matchup": "Bragantino vs Atletico Mineiro",
      "league": "BRAZIL - SERIE A",
      "bet": "Over 2.5",
      "betbck_odds": "+139",
      "pinnacle_nvp": "+127",
      "ev": "5.43%",
      "ev_val": 0.054299999999999994,
      "start_time": "08/03 17:30",
      "event_id": 1612142715
    },
    {
      "matchup": "Silkeborg vs Randers",
      "league": "DENMARK - SUPERLIGA",
      "bet": "Under 2.5",
      "betbck_odds": "+132",
      "pinnacle_nvp": "+120",
      "ev": "5.41%",
      "ev_val": 0.0541,
      "start_time": "08/03 08:00",
      "event_id": 1612107737
    },
    {
      "matchup": "Qingdao Hainiu vs Dalian Yingbo",
      "league": "CHINA - CHINESE SUPER LEAGUE",
      "bet": "Dalian Yingbo -0.5",
      "betbck_odds": "-128",
      "pinnacle_nvp": "-144",
      "ev": "5.21%",
      "ev_val": 0.0521,
      "start_time": "08/03 07:00",
      "event_id": 1612115025
    },
    {
      "matchup": "Pachuca vs Atlas",
      "league": "MEXICO - LIGA MX",
      "bet": "Under 2.5",
      "betbck_odds": "+119",
      "pinnacle_nvp": "+110",
      "ev": "4.14%",
      "ev_val": 0.0414,
      "start_time": "08/09 23:00",
      "event_id": 1612428512
    },
    {
      "matchup": "Puebla vs Tigres UANL",
      "league": "MEXICO - LIGA MX",
      "bet": "Over 2.5",
      "betbck_odds": "+117",
      "pinnacle_nvp": "+110",
      "ev": "3.19%",
      "ev_val": 0.0319,
      "start_time": "08/08 23:00",
      "event_id": 1612357095
    },
    {
      "matchup": "Houston Dynamo vs Austin FC",
      "league": "USA - MLS",
      "bet": "Over 2.5",
      "betbck_odds": "+127",
      "pinnacle_nvp": "+120",
      "ev": "2.95%",
      "ev_val": 0.029500000000000002,
      "start_time": "08/09 20:30",
      "event_id": 1612249517
    },
    {
      "matchup": "Orenburg vs Baltika Kaliningrad",
      "league": "RUSSIA - PREMIER LEAGUE",
      "bet": "Over 2.5",
      "betbck_odds": "+115",
      "pinnacle_nvp": "+109",
      "ev": "2.67%",
      "ev_val": 0.026699999999999998,
      "start_time": "08/03 08:45",
      "event_id": 1612241830
    },
    {
      "matchup": "CSKA Moscow vs Zenit",
      "league": "RUSSIA - PREMIER LEAGUE",
      "bet": "Zenit -1",
      "betbck_odds": "+127",
      "pinnacle_nvp": "+122",
      "ev": "2.44%",
      "ev_val": 0.024399999999999998,
      "start_time": "08/03 11:00",
      "event_id": 1611608936
    },
    {
      "matchup": "Club Tijuana vs Mazatlan",
      "league": "MEXICO - LIGA MX",
      "bet": "Club Tijuana 0",
      "betbck_odds": "+119",
      "pinnacle_nvp": "+114",
      "ev": "2.38%",
      "ev_val": 0.023799999999999998,
      "start_time": "08/09 23:00",
      "event_id": 1612421787
    },
    {
      "matchup": "Juan Pablo II College vs FBC Melgar",
      "league": "PERU - PRIMERA DIVISION",
      "bet": "ML - FBC Melgar",
      "betbck_odds": "-397",
      "pinnacle_nvp": "-446",
      "ev": "2.28%",
      "ev_val": 0.022799999999999997,
      "start_time": "08/05 16:00",
      "event_id": 1612219745
    },
    {
      "matchup": "Bryne vs Molde",
      "league": "NORWAY - ELITESERIEN",
      "bet": "Bryne 1",
      "betbck_odds": "+107",
      "pinnacle_nvp": "+103",
      "ev": "1.97%",
      "ev_val": 0.0197,
      "start_time": "08/03 11:00",
      "event_id": 1612138809
    },
    {
      "matchup": "Banik Ostrava vs Dukla Prague",
      "league": "CZECH REPUBLIC - FIRST LEAGUE",
      "bet": "Under 2.5",
      "betbck_odds": "+123",
      "pinnacle_nvp": "+119",
      "ev": "1.83%",
      "ev_val": 0.0183,
      "start_time": "08/03 11:30",
      "event_id": 1612137366
    },
    {
      "matchup": "FC Nordsjaelland vs Sonderjyske",
      "league": "DENMARK - SUPERLIGA",
      "bet": "Over 3.0",
      "betbck_odds": "+125",
      "pinnacle_nvp": "+121",
      "ev": "1.76%",
      "ev_val": 0.0176,
      "start_time": "08/03 08:00",
      "event_id": 1612137414
    },
    {
      "matchup": "Sarmiento de Junin vs San Martin de San Juan",
      "league": "ARGENTINA - LIGA PROFESIONAL",
      "bet": "Under 1.5",
      "betbck_odds": "+134",
      "pinnacle_nvp": "+130",
      "ev": "1.74%",
      "ev_val": 0.0174,
      "start_time": "08/09 13:30",
      "event_id": 1612412158
    },
    {
      "matchup": "Nashville SC vs St Louis City SC",
      "league": "USA - MLS",
      "bet": "Over 3.0",
      "betbck_odds": "+125",
      "pinnacle_nvp": "+121",
      "ev": "1.58%",
      "ev_val": 0.0158,
      "start_time": "08/09 20:30",
      "event_id": 1612249518
    },
    {
      "matchup": "Orenburg vs Baltika Kaliningrad",
      "league": "RUSSIA - PREMIER LEAGUE",
      "bet": "ML - Baltika Kaliningrad",
      "betbck_odds": "-137",
      "pinnacle_nvp": "-142",
      "ev": "1.46%",
      "ev_val": 0.0146,
      "start_time": "08/03 08:45",
      "event_id": 1612241830
    },
    {
      "matchup": "Bodo Glimt vs Ham-Kam",
      "league": "NORWAY - ELITESERIEN",
      "bet": "Over 3.5",
      "betbck_odds": "+125",
      "pinnacle_nvp": "+122",
      "ev": "1.31%",
      "ev_val": 0.0131,
      "start_time": "08/03 08:30",
      "event_id": 1612137291
    },
    {
      "matchup": "Club Tijuana vs Mazatlan",
      "league": "MEXICO - LIGA MX",
      "bet": "Under 2.5",
      "betbck_odds": "+113",
      "pinnacle_nvp": "+110",
      "ev": "1.28%",
      "ev_val": 0.0128,
      "start_time": "08/09 23:00",
      "event_id": 1612421787
    },
    {
      "matchup": "Portland Timbers vs FC Dallas",
      "league": "USA - MLS",
      "bet": "Over 3.0",
      "betbck_odds": "+129",
      "pinnacle_nvp": "+126",
      "ev": "1.28%",
      "ev_val": 0.0128,
      "start_time": "08/09 20:30",
      "event_id": 1612252373
    },
    {
      "matchup": "Orenburg vs Baltika Kaliningrad",
      "league": "RUSSIA - PREMIER LEAGUE",
      "bet": "Baltika Kaliningrad -0.5",
      "betbck_odds": "-137",
      "pinnacle_nvp": "-141",
      "ev": "1.17%",
      "ev_val": 0.011699999999999999,
      "start_time": "08/03 08:45",
      "event_id": 1612241830
    },
    {
      "matchup": "Rosario Central vs Atletico Tucuman",
      "league": "ARGENTINA - LIGA PROFESIONAL",
      "bet": "Over 2.0",
      "betbck_odds": "+102",
      "pinnacle_nvp": "+100",
      "ev": "1.00%",
      "ev_val": 0.01,
      "start_time": "08/09 19:45",
      "event_id": 1612421750
    },
    {
      "matchup": "Yenisey Krasnoyarsk vs Rotor Volgograd",
      "league": "RUSSIA - FNL",
      "bet": "ML - Rotor Volgograd",
      "betbck_odds": "-102",
      "pinnacle_nvp": "-104",
      "ev": "0.99%",
      "ev_val": 0.009899999999999999,
      "start_time": "08/04 13:00",
      "event_id": 1612205624
    },
    {
      "matchup": "Harju JK Laagri vs Paide Linnameeskond",
      "league": "ESTONIA - MEISTRILIIGA",
      "bet": "ML - Paide Linnameeskond",
      "betbck_odds": "-415",
      "pinnacle_nvp": "-437",
      "ev": "0.97%",
      "ev_val": 0.0097,
      "start_time": "08/03 10:00",
      "event_id": 1612184253
    },
    {
      "matchup": "Rakow Czestochowa vs Radomiak Radom",
      "league": "POLAND - EKSTRAKLASA",
      "bet": "Over 2.5",
      "betbck_odds": "+134",
      "pinnacle_nvp": "+132",
      "ev": "0.78%",
      "ev_val": 0.0078000000000000005,
      "start_time": "08/03 11:30",
      "event_id": 1612137492
    },
    {
      "matchup": "Arda vs Botev Plovdiv",
      "league": "BULGARIA - PARVA LEAGUE",
      "bet": "ML - Botev Plovdiv",
      "betbck_odds": "-127",
      "pinnacle_nvp": "-129",
      "ev": "0.76%",
      "ev_val": 0.0076,
      "start_time": "08/04 14:15",
      "event_id": 1612184298
    },
    {
      "matchup": "Vinotinto Ecuador vs Delfin",
      "league": "ECUADOR - SERIE A",
      "bet": "ML - Delfin",
      "betbck_odds": "+101",
      "pinnacle_nvp": "-100",
      "ev": "0.70%",
      "ev_val": 0.006999999999999999,
      "start_time": "08/04 20:00",
      "event_id": 1612188574
    },
    {
      "matchup": "Manta vs Tecnico Universitario",
      "league": "ECUADOR - SERIE A",
      "bet": "ML - Tecnico Universitario",
      "betbck_odds": "-152",
      "pinnacle_nvp": "-155",
      "ev": "0.66%",
      "ev_val": 0.0066,
      "start_time": "08/03 16:30",
      "event_id": 1612184319
    },
    {
      "matchup": "Osters vs Sirius",
      "league": "SWEDEN - ALLSVENSKAN",
      "bet": "Over 3.0",
      "betbck_odds": "+125",
      "pinnacle_nvp": "+124",
      "ev": "0.63%",
      "ev_val": 0.0063,
      "start_time": "08/03 10:30",
      "event_id": 1612137474
    },
    {
      "matchup": "Mjallby vs Malmo",
      "league": "SWEDEN - ALLSVENSKAN",
      "bet": "Under 2.5",
      "betbck_odds": "+110",
      "pinnacle_nvp": "+109",
      "ev": "0.62%",
      "ev_val": 0.0062,
      "start_time": "08/09 09:00",
      "event_id": 1612383609
    },
    {
      "matchup": "Emelec vs Libertad Loja",
      "league": "ECUADOR - SERIE A",
      "bet": "ML - Emelec",
      "betbck_odds": "+134",
      "pinnacle_nvp": "+133",
      "ev": "0.60%",
      "ev_val": 0.006,
      "start_time": "08/03 19:00",
      "event_id": 1612193774
    },
    {
      "matchup": "San Diego FC vs Sporting Kansas City",
      "league": "USA - MLS",
      "bet": "Under 3.0",
      "betbck_odds": "+105",
      "pinnacle_nvp": "+104",
      "ev": "0.59%",
      "ev_val": 0.0059,
      "start_time": "08/09 20:45",
      "event_id": 1612249513
    },
    {
      "matchup": "Talleres de Cordoba vs Lanus",
      "league": "ARGENTINA - LIGA PROFESIONAL",
      "bet": "Over 2.0",
      "betbck_odds": "+107",
      "pinnacle_nvp": "+106",
      "ev": "0.58%",
      "ev_val": 0.0058,
      "start_time": "08/08 20:15",
      "event_id": 1612374624
    },
    {
      "matchup": "Racing Club vs Boca Juniors",
      "league": "ARGENTINA - LIGA PROFESIONAL",
      "bet": "Under 2.0",
      "betbck_odds": "+117",
      "pinnacle_nvp": "+116",
      "ev": "0.51%",
      "ev_val": 0.0051,
      "start_time": "08/09 15:30",
      "event_id": 1612421710
    },
    {
      "matchup": "Rosario Central vs Atletico Tucuman",
      "league": "ARGENTINA - LIGA PROFESIONAL",
      "bet": "Atletico Tucuman 0",
      "betbck_odds": "+117",
      "pinnacle_nvp": "+116",
      "ev": "0.51%",
      "ev_val": 0.0051,
      "start_time": "08/09 19:45",
      "event_id": 1612421750
    },
    {
      "matchup": "Huracan vs CA Tigre",
      "league": "ARGENTINA - LIGA PROFESIONAL",
      "bet": "Huracan 0",
      "betbck_odds": "+127",
      "pinnacle_nvp": "+126",
      "ev": "0.40%",
      "ev_val": 0.004,
      "start_time": "08/08 18:00",
      "event_id": 1612349359
    },
    {
      "matchup": "San Marcos vs Santiago Wanderers",
      "league": "CHILE - PRIMERA B DIVISION",
      "bet": "Santiago Wanderers -0.5",
      "betbck_odds": "-105",
      "pinnacle_nvp": "-106",
      "ev": "0.33%",
      "ev_val": 0.0033,
      "start_time": "08/03 20:00",
      "event_id": 1612188561
    },
    {
      "matchup": "Harju JK Laagri vs Paide Linnameeskond",
      "league": "ESTONIA - MEISTRILIIGA",
      "bet": "Harju JK Laagri 2",
      "betbck_odds": "-128",
      "pinnacle_nvp": "-129",
      "ev": "0.30%",
      "ev_val": 0.003,
      "start_time": "08/03 10:00",
      "event_id": 1612184253
    },
    {
      "matchup": "San Marcos vs Santiago Wanderers",
      "league": "CHILE - PRIMERA B DIVISION",
      "bet": "ML - Santiago Wanderers",
      "betbck_odds": "-105",
      "pinnacle_nvp": "-106",
      "ev": "0.28%",
      "ev_val": 0.0028000000000000004,
      "start_time": "08/03 20:00",
      "event_id": 1612188561
    },
    {
      "matchup": "Urawa Red Diamonds vs Yokohama FC",
      "league": "JAPAN - J1 LEAGUE",
      "bet": "Over 2.5",
      "betbck_odds": "+113",
      "pinnacle_nvp": "+112",
      "ev": "0.28%",
      "ev_val": 0.0028000000000000004,
      "start_time": "08/09 05:00",
      "event_id": 1612249510
    },
    {
      "matchup": "Midtjylland vs AGF",
      "league": "DENMARK - SUPERLIGA",
      "bet": "AGF 0",
      "betbck_odds": "+108",
      "pinnacle_nvp": "+108",
      "ev": "0.24%",
      "ev_val": 0.0024,
      "start_time": "08/03 10:00",
      "event_id": 1612138784
    },
    {
      "matchup": "Degerfors vs IFK Goteborg",
      "league": "SWEDEN - ALLSVENSKAN",
      "bet": "Under 2.5",
      "betbck_odds": "+123",
      "pinnacle_nvp": "+123",
      "ev": "0.22%",
      "ev_val": 0.0022,
      "start_time": "08/04 13:00",
      "event_id": 1612182539
    },
    {
      "matchup": "Gimnasia La Plata vs Godoy Cruz",
      "league": "ARGENTINA - LIGA PROFESIONAL",
      "bet": "Over 2.0",
      "betbck_odds": "+129",
      "pinnacle_nvp": "+129",
      "ev": "0.17%",
      "ev_val": 0.0017000000000000001,
      "start_time": "08/07 16:00",
      "event_id": 1612294742
    },
    {
      "matchup": "CSKA Moscow vs Zenit",
      "league": "RUSSIA - PREMIER LEAGUE",
      "bet": "ML - Zenit",
      "betbck_odds": "-146",
      "pinnacle_nvp": "-147",
      "ev": "0.17%",
      "ev_val": 0.0017000000000000001,
      "start_time": "08/03 11:00",
      "event_id": 1611608936
    },
    {
      "matchup": "Arda vs Botev Plovdiv",
      "league": "BULGARIA - PARVA LEAGUE",
      "bet": "Botev Plovdiv -0.5",
      "betbck_odds": "-127",
      "pinnacle_nvp": "-127",
      "ev": "0.13%",
      "ev_val": 0.0013,
      "start_time": "08/04 14:15",
      "event_id": 1612184298
    },
    {
      "matchup": "Avispa Fukuoka vs Kawasaki Frontale",
      "league": "JAPAN - J1 LEAGUE",
      "bet": "Over 2.5",
      "betbck_odds": "+134",
      "pinnacle_nvp": "+134",
      "ev": "0.09%",
      "ev_val": 0.0009,
      "start_time": "08/09 06:00",
      "event_id": 1612252367
    },
    {
      "matchup": "Yokohama F. Marinos vs Tokyo Verdy",
      "league": "JAPAN - J1 LEAGUE",
      "bet": "Over 2.5",
      "betbck_odds": "+102",
      "pinnacle_nvp": "+102",
      "ev": "0.05%",
      "ev_val": 0.0005,
      "start_time": "08/09 05:00",
      "event_id": 1612252371
    },
    {
      "matchup": "Halmstads vs Djurgardens",
      "league": "SWEDEN - ALLSVENSKAN",
      "bet": "Over 3.0",
      "betbck_odds": "+110",
      "pinnacle_nvp": "+110",
      "ev": "0.05%",
      "ev_val": 0.0005,
      "start_time": "08/03 08:00",
      "event_id": 1612115053
    },
    {
      "matchup": "Yenisey Krasnoyarsk vs Rotor Volgograd",
      "league": "RUSSIA - FNL",
      "bet": "Rotor Volgograd -0.5",
      "betbck_odds": "-102",
      "pinnacle_nvp": "-102",
      "ev": "-0.03%",
      "ev_val": -0.0003,
      "start_time": "08/04 13:00",
      "event_id": 1612205624
    },
    {
      "matchup": "Akhmat Grozny vs Dynamo Makhachkala",
      "league": "RUSSIA - PREMIER LEAGUE",
      "bet": "ML - Akhmat Grozny",
      "betbck_odds": "+172",
      "pinnacle_nvp": "+172",
      "ev": "-0.04%",
      "ev_val": -0.0004,
      "start_time": "08/03 13:30",
      "event_id": 1611608938
    }
  ],
  "last_run": "2025-08-02T23:18:39.650853",
  "total_processed": 189,
  "total_matched": 185,
  "total_with_ev": 882,
  "match_rate": 97.88359788359789,
  "ev_rate": 476.7567567567568
}